mux/mux2bit.v
module mux_2bit(out, select, in0, in1);
    input select;
    input in0, in1;
    output out;

    assign out = select ? in1 : in0;
endmodule

mux/mux4bit.v
module mux_4bit(out, select, in0, in1, in2, in3);
    input [1:0] select;
    input in0, in1, in2, in3;
    output out;

    wire w1, w2;

    mux_2bit m1(w1, select[0], in0, in1);
    mux_2bit m2(w2, select[0], in2, in3);
    mux_2bit m3(out, select[1], w1, w2);
endmodule

mux/mux8bit.v
module mux_8bit(out, select, in0, in1, in2, in3, in4, in5, in6, in7);
    input [2:0] select;
    input in0, in1, in2, in3, in4, in5, in6, in7;
    output out;

    wire w1, w2;

    mux_4bit m1(w1, select[1:0], in0, in1, in2, in3);
    mux_4bit m2(w2, select[1:0], in4, in5, in6, in7);
    mux_2bit m3(out, select[2], w1, w2);
endmodule

alu/comparators/comp_2.v
module comp_2(EQ1, GT1, A, B, EQ0, GT0);
    input EQ1, GT1;
    input [1:0] A, B;
    output EQ0, GT0;


    //notA and notB
    wire[1:0] notA, notB;

    not n1(notA[1], A[1]);
    not n1(notA[0], A[0]);
    not n1(notB[1], B[1]);
    not n1(notB[0], B[0]);

    wire selectBits[2:1];

    assign selectBits[2] = A[1];
    assign selectBits[1] = A[0];
    assign selectBits[0] = B[1];


    wire eqmux, gtmux;
    
    mux_8bit EQout(eqmux, selectBits, notB[0], 1'b0, B[0], 1'b0, 1'b0, notB[0], 1'b0, B[0]);

    mux_8bit GTout(gtmux, selectBits, 1'b0, 1'b0, notB[0], 1'b0, 1'b1, 1'b0, 1'b1, notB[0]);


    //evaluating EQ_out
    wire EQandnotGTin, notGT1, notEQ1;

    not notGTinand(notGT1, GT1);
    not notEQinand(notEQ1, EQ1);

    wire EQ1andnotGT1forEQ0;


    and jeronimo(EQ0, eqmux, EQ1, notGT1);

    wire justin, smith;

    and jj(justin, gtmux, EQ1, notGT1);
    and ss(smith, notEQ1, GT1);

    or suckItBozo(GT0, justin, smith);

endmodule

alu/comparators/comp_4.v
module comp_4(EQ1, GT1, A, B, EQ0, GT0);
    input EQ1, GT1;
    input [3:0] A, B;
    output EQ0, GT0;

    wire  eq, gt;
    comp_2 c1(EQ1, GT1, A[3:2], B[3:2], eq, gt);
    comp_2 c2(eq, gt, A[1:0], B[1:0], EQ0, GT0);
endmodule

alu/comparators/comp_8.v
module comp_8(EQ1, GT1, A, B, EQ0, GT0);
    input EQ1, GT1;
    input [7:0] A, B;
    output EQ0, GT0;

    wire eq, gt;
    comp_4 c1(EQ1, GT1, A[7:4], B[7:4], eq, gt);
    comp_4 c2(eq, gt, A[3:0], B[3:0], EQ0, GT0);
endmodule

comp_2_tb.v
`timescale 1 ns / 100 ps
module comp_2_tb;
    wire [7:0] A, B;
    wire EQ1, GT1;
    wire EQ0, GT0;

    comp_8 c1(.EQ1(EQ1), .GT1(GT1), .A(A), .B(B), .EQ0(EQ0), .GT0(GT0));

    integer i;
    assign {A, B, EQ1, GT1} = i;


    initial begin
        for (i = 0; i < 256; i = i + 1) begin
            #20;
            $display("A = %b, B = %b, EQ0 = %b, GT0 = %b, EQ1 = %b, GT1 = %b", A, B, EQ0, GT0, EQ1, GT1);
        end
        $finish;
    end

    initial begin
        $dumpfile("comp_2_tb.vcd");
        $dumpvars(0, comp_2_tb);
    end
endmodule

comp_2_tb.vcd
$date
	Fri Feb  9 12:36:30 2024
$end
$version
	Icarus Verilog
$end
$timescale
	100ps
$end
$scope module comp_2_tb $end
$var wire 1 ! GT1 $end
$var wire 1 " GT0 $end
$var wire 1 # EQ1 $end
$var wire 1 $ EQ0 $end
$var wire 8 % B [7:0] $end
$var wire 8 & A [7:0] $end
$var integer 32 ' i [31:0] $end
$scope module c1 $end
$var wire 8 ( A [7:0] $end
$var wire 8 ) B [7:0] $end
$var wire 1 # EQ1 $end
$var wire 1 ! GT1 $end
$var wire 1 * gt $end
$var wire 1 + eq $end
$var wire 1 " GT0 $end
$var wire 1 $ EQ0 $end
$scope module c1 $end
$var wire 4 , A [3:0] $end
$var wire 4 - B [3:0] $end
$var wire 1 # EQ1 $end
$var wire 1 ! GT1 $end
$var wire 1 . gt $end
$var wire 1 / eq $end
$var wire 1 * GT0 $end
$var wire 1 + EQ0 $end
$scope module c1 $end
$var wire 2 0 A [1:0] $end
$var wire 2 1 B [1:0] $end
$var wire 1 / EQ0 $end
$var wire 1 # EQ1 $end
$var wire 1 . GT0 $end
$var wire 1 ! GT1 $end
$var wire 1 2 justin $end
$var wire 1 3 notEQ1 $end
$var wire 1 4 notGT1 $end
$var wire 1 5 smith $end
$var wire 3 6 selectBits [2:0] $end
$var wire 2 7 notB [1:0] $end
$var wire 2 8 notA [1:0] $end
$var wire 1 9 gtmux $end
$var wire 1 : eqmux $end
$scope module EQout $end
$var wire 1 ; in0 $end
$var wire 1 < in1 $end
$var wire 1 = in2 $end
$var wire 1 > in3 $end
$var wire 1 ? in4 $end
$var wire 1 @ in5 $end
$var wire 1 A in6 $end
$var wire 1 B in7 $end
$var wire 3 C select [2:0] $end
$var wire 1 D w2 $end
$var wire 1 E w1 $end
$var wire 1 : out $end
$scope module m1 $end
$var wire 1 ; in0 $end
$var wire 1 < in1 $end
$var wire 1 = in2 $end
$var wire 1 > in3 $end
$var wire 2 F select [1:0] $end
$var wire 1 G w2 $end
$var wire 1 H w1 $end
$var wire 1 E out $end
$scope module m1 $end
$var wire 1 ; in0 $end
$var wire 1 < in1 $end
$var wire 1 I select $end
$var wire 1 H out $end
$upscope $end
$scope module m2 $end
$var wire 1 = in0 $end
$var wire 1 > in1 $end
$var wire 1 J select $end
$var wire 1 G out $end
$upscope $end
$scope module m3 $end
$var wire 1 H in0 $end
$var wire 1 G in1 $end
$var wire 1 K select $end
$var wire 1 E out $end
$upscope $end
$upscope $end
$scope module m2 $end
$var wire 1 ? in0 $end
$var wire 1 @ in1 $end
$var wire 1 A in2 $end
$var wire 1 B in3 $end
$var wire 2 L select [1:0] $end
$var wire 1 M w2 $end
$var wire 1 N w1 $end
$var wire 1 D out $end
$scope module m1 $end
$var wire 1 ? in0 $end
$var wire 1 @ in1 $end
$var wire 1 O select $end
$var wire 1 N out $end
$upscope $end
$scope module m2 $end
$var wire 1 A in0 $end
$var wire 1 B in1 $end
$var wire 1 P select $end
$var wire 1 M out $end
$upscope $end
$scope module m3 $end
$var wire 1 N in0 $end
$var wire 1 M in1 $end
$var wire 1 Q select $end
$var wire 1 D out $end
$upscope $end
$upscope $end
$scope module m3 $end
$var wire 1 E in0 $end
$var wire 1 D in1 $end
$var wire 1 R select $end
$var wire 1 : out $end
$upscope $end
$upscope $end
$scope module GTout $end
$var wire 1 S in0 $end
$var wire 1 T in1 $end
$var wire 1 U in2 $end
$var wire 1 V in3 $end
$var wire 1 W in4 $end
$var wire 1 X in5 $end
$var wire 1 Y in6 $end
$var wire 1 Z in7 $end
$var wire 3 [ select [2:0] $end
$var wire 1 \ w2 $end
$var wire 1 ] w1 $end
$var wire 1 9 out $end
$scope module m1 $end
$var wire 1 S in0 $end
$var wire 1 T in1 $end
$var wire 1 U in2 $end
$var wire 1 V in3 $end
$var wire 2 ^ select [1:0] $end
$var wire 1 _ w2 $end
$var wire 1 ` w1 $end
$var wire 1 ] out $end
$scope module m1 $end
$var wire 1 S in0 $end
$var wire 1 T in1 $end
$var wire 1 a select $end
$var wire 1 ` out $end
$upscope $end
$scope module m2 $end
$var wire 1 U in0 $end
$var wire 1 V in1 $end
$var wire 1 b select $end
$var wire 1 _ out $end
$upscope $end
$scope module m3 $end
$var wire 1 ` in0 $end
$var wire 1 _ in1 $end
$var wire 1 c select $end
$var wire 1 ] out $end
$upscope $end
$upscope $end
$scope module m2 $end
$var wire 1 W in0 $end
$var wire 1 X in1 $end
$var wire 1 Y in2 $end
$var wire 1 Z in3 $end
$var wire 2 d select [1:0] $end
$var wire 1 e w2 $end
$var wire 1 f w1 $end
$var wire 1 \ out $end
$scope module m1 $end
$var wire 1 W in0 $end
$var wire 1 X in1 $end
$var wire 1 g select $end
$var wire 1 f out $end
$upscope $end
$scope module m2 $end
$var wire 1 Y in0 $end
$var wire 1 Z in1 $end
$var wire 1 h select $end
$var wire 1 e out $end
$upscope $end
$scope module m3 $end
$var wire 1 f in0 $end
$var wire 1 e in1 $end
$var wire 1 i select $end
$var wire 1 \ out $end
$upscope $end
$upscope $end
$scope module m3 $end
$var wire 1 ] in0 $end
$var wire 1 \ in1 $end
$var wire 1 j select $end
$var wire 1 9 out $end
$upscope $end
$upscope $end
$upscope $end
$scope module c2 $end
$var wire 2 k A [1:0] $end
$var wire 2 l B [1:0] $end
$var wire 1 + EQ0 $end
$var wire 1 / EQ1 $end
$var wire 1 * GT0 $end
$var wire 1 . GT1 $end
$var wire 1 m justin $end
$var wire 1 n notEQ1 $end
$var wire 1 o notGT1 $end
$var wire 1 p smith $end
$var wire 3 q selectBits [2:0] $end
$var wire 2 r notB [1:0] $end
$var wire 2 s notA [1:0] $end
$var wire 1 t gtmux $end
$var wire 1 u eqmux $end
$scope module EQout $end
$var wire 1 v in0 $end
$var wire 1 w in1 $end
$var wire 1 x in2 $end
$var wire 1 y in3 $end
$var wire 1 z in4 $end
$var wire 1 { in5 $end
$var wire 1 | in6 $end
$var wire 1 } in7 $end
$var wire 3 ~ select [2:0] $end
$var wire 1 !" w2 $end
$var wire 1 "" w1 $end
$var wire 1 u out $end
$scope module m1 $end
$var wire 1 v in0 $end
$var wire 1 w in1 $end
$var wire 1 x in2 $end
$var wire 1 y in3 $end
$var wire 2 #" select [1:0] $end
$var wire 1 $" w2 $end
$var wire 1 %" w1 $end
$var wire 1 "" out $end
$scope module m1 $end
$var wire 1 v in0 $end
$var wire 1 w in1 $end
$var wire 1 &" select $end
$var wire 1 %" out $end
$upscope $end
$scope module m2 $end
$var wire 1 x in0 $end
$var wire 1 y in1 $end
$var wire 1 '" select $end
$var wire 1 $" out $end
$upscope $end
$scope module m3 $end
$var wire 1 %" in0 $end
$var wire 1 $" in1 $end
$var wire 1 (" select $end
$var wire 1 "" out $end
$upscope $end
$upscope $end
$scope module m2 $end
$var wire 1 z in0 $end
$var wire 1 { in1 $end
$var wire 1 | in2 $end
$var wire 1 } in3 $end
$var wire 2 )" select [1:0] $end
$var wire 1 *" w2 $end
$var wire 1 +" w1 $end
$var wire 1 !" out $end
$scope module m1 $end
$var wire 1 z in0 $end
$var wire 1 { in1 $end
$var wire 1 ," select $end
$var wire 1 +" out $end
$upscope $end
$scope module m2 $end
$var wire 1 | in0 $end
$var wire 1 } in1 $end
$var wire 1 -" select $end
$var wire 1 *" out $end
$upscope $end
$scope module m3 $end
$var wire 1 +" in0 $end
$var wire 1 *" in1 $end
$var wire 1 ." select $end
$var wire 1 !" out $end
$upscope $end
$upscope $end
$scope module m3 $end
$var wire 1 "" in0 $end
$var wire 1 !" in1 $end
$var wire 1 /" select $end
$var wire 1 u out $end
$upscope $end
$upscope $end
$scope module GTout $end
$var wire 1 0" in0 $end
$var wire 1 1" in1 $end
$var wire 1 2" in2 $end
$var wire 1 3" in3 $end
$var wire 1 4" in4 $end
$var wire 1 5" in5 $end
$var wire 1 6" in6 $end
$var wire 1 7" in7 $end
$var wire 3 8" select [2:0] $end
$var wire 1 9" w2 $end
$var wire 1 :" w1 $end
$var wire 1 t out $end
$scope module m1 $end
$var wire 1 0" in0 $end
$var wire 1 1" in1 $end
$var wire 1 2" in2 $end
$var wire 1 3" in3 $end
$var wire 2 ;" select [1:0] $end
$var wire 1 <" w2 $end
$var wire 1 =" w1 $end
$var wire 1 :" out $end
$scope module m1 $end
$var wire 1 0" in0 $end
$var wire 1 1" in1 $end
$var wire 1 >" select $end
$var wire 1 =" out $end
$upscope $end
$scope module m2 $end
$var wire 1 2" in0 $end
$var wire 1 3" in1 $end
$var wire 1 ?" select $end
$var wire 1 <" out $end
$upscope $end
$scope module m3 $end
$var wire 1 =" in0 $end
$var wire 1 <" in1 $end
$var wire 1 @" select $end
$var wire 1 :" out $end
$upscope $end
$upscope $end
$scope module m2 $end
$var wire 1 4" in0 $end
$var wire 1 5" in1 $end
$var wire 1 6" in2 $end
$var wire 1 7" in3 $end
$var wire 2 A" select [1:0] $end
$var wire 1 B" w2 $end
$var wire 1 C" w1 $end
$var wire 1 9" out $end
$scope module m1 $end
$var wire 1 4" in0 $end
$var wire 1 5" in1 $end
$var wire 1 D" select $end
$var wire 1 C" out $end
$upscope $end
$scope module m2 $end
$var wire 1 6" in0 $end
$var wire 1 7" in1 $end
$var wire 1 E" select $end
$var wire 1 B" out $end
$upscope $end
$scope module m3 $end
$var wire 1 C" in0 $end
$var wire 1 B" in1 $end
$var wire 1 F" select $end
$var wire 1 9" out $end
$upscope $end
$upscope $end
$scope module m3 $end
$var wire 1 :" in0 $end
$var wire 1 9" in1 $end
$var wire 1 G" select $end
$var wire 1 t out $end
$upscope $end
$upscope $end
$upscope $end
$upscope $end
$scope module c2 $end
$var wire 4 H" A [3:0] $end
$var wire 4 I" B [3:0] $end
$var wire 1 + EQ1 $end
$var wire 1 * GT1 $end
$var wire 1 J" gt $end
$var wire 1 K" eq $end
$var wire 1 " GT0 $end
$var wire 1 $ EQ0 $end
$scope module c1 $end
$var wire 2 L" A [1:0] $end
$var wire 2 M" B [1:0] $end
$var wire 1 K" EQ0 $end
$var wire 1 + EQ1 $end
$var wire 1 J" GT0 $end
$var wire 1 * GT1 $end
$var wire 1 N" justin $end
$var wire 1 O" notEQ1 $end
$var wire 1 P" notGT1 $end
$var wire 1 Q" smith $end
$var wire 3 R" selectBits [2:0] $end
$var wire 2 S" notB [1:0] $end
$var wire 2 T" notA [1:0] $end
$var wire 1 U" gtmux $end
$var wire 1 V" eqmux $end
$scope module EQout $end
$var wire 1 W" in0 $end
$var wire 1 X" in1 $end
$var wire 1 Y" in2 $end
$var wire 1 Z" in3 $end
$var wire 1 [" in4 $end
$var wire 1 \" in5 $end
$var wire 1 ]" in6 $end
$var wire 1 ^" in7 $end
$var wire 3 _" select [2:0] $end
$var wire 1 `" w2 $end
$var wire 1 a" w1 $end
$var wire 1 V" out $end
$scope module m1 $end
$var wire 1 W" in0 $end
$var wire 1 X" in1 $end
$var wire 1 Y" in2 $end
$var wire 1 Z" in3 $end
$var wire 2 b" select [1:0] $end
$var wire 1 c" w2 $end
$var wire 1 d" w1 $end
$var wire 1 a" out $end
$scope module m1 $end
$var wire 1 W" in0 $end
$var wire 1 X" in1 $end
$var wire 1 e" select $end
$var wire 1 d" out $end
$upscope $end
$scope module m2 $end
$var wire 1 Y" in0 $end
$var wire 1 Z" in1 $end
$var wire 1 f" select $end
$var wire 1 c" out $end
$upscope $end
$scope module m3 $end
$var wire 1 d" in0 $end
$var wire 1 c" in1 $end
$var wire 1 g" select $end
$var wire 1 a" out $end
$upscope $end
$upscope $end
$scope module m2 $end
$var wire 1 [" in0 $end
$var wire 1 \" in1 $end
$var wire 1 ]" in2 $end
$var wire 1 ^" in3 $end
$var wire 2 h" select [1:0] $end
$var wire 1 i" w2 $end
$var wire 1 j" w1 $end
$var wire 1 `" out $end
$scope module m1 $end
$var wire 1 [" in0 $end
$var wire 1 \" in1 $end
$var wire 1 k" select $end
$var wire 1 j" out $end
$upscope $end
$scope module m2 $end
$var wire 1 ]" in0 $end
$var wire 1 ^" in1 $end
$var wire 1 l" select $end
$var wire 1 i" out $end
$upscope $end
$scope module m3 $end
$var wire 1 j" in0 $end
$var wire 1 i" in1 $end
$var wire 1 m" select $end
$var wire 1 `" out $end
$upscope $end
$upscope $end
$scope module m3 $end
$var wire 1 a" in0 $end
$var wire 1 `" in1 $end
$var wire 1 n" select $end
$var wire 1 V" out $end
$upscope $end
$upscope $end
$scope module GTout $end
$var wire 1 o" in0 $end
$var wire 1 p" in1 $end
$var wire 1 q" in2 $end
$var wire 1 r" in3 $end
$var wire 1 s" in4 $end
$var wire 1 t" in5 $end
$var wire 1 u" in6 $end
$var wire 1 v" in7 $end
$var wire 3 w" select [2:0] $end
$var wire 1 x" w2 $end
$var wire 1 y" w1 $end
$var wire 1 U" out $end
$scope module m1 $end
$var wire 1 o" in0 $end
$var wire 1 p" in1 $end
$var wire 1 q" in2 $end
$var wire 1 r" in3 $end
$var wire 2 z" select [1:0] $end
$var wire 1 {" w2 $end
$var wire 1 |" w1 $end
$var wire 1 y" out $end
$scope module m1 $end
$var wire 1 o" in0 $end
$var wire 1 p" in1 $end
$var wire 1 }" select $end
$var wire 1 |" out $end
$upscope $end
$scope module m2 $end
$var wire 1 q" in0 $end
$var wire 1 r" in1 $end
$var wire 1 ~" select $end
$var wire 1 {" out $end
$upscope $end
$scope module m3 $end
$var wire 1 |" in0 $end
$var wire 1 {" in1 $end
$var wire 1 !# select $end
$var wire 1 y" out $end
$upscope $end
$upscope $end
$scope module m2 $end
$var wire 1 s" in0 $end
$var wire 1 t" in1 $end
$var wire 1 u" in2 $end
$var wire 1 v" in3 $end
$var wire 2 "# select [1:0] $end
$var wire 1 ## w2 $end
$var wire 1 $# w1 $end
$var wire 1 x" out $end
$scope module m1 $end
$var wire 1 s" in0 $end
$var wire 1 t" in1 $end
$var wire 1 %# select $end
$var wire 1 $# out $end
$upscope $end
$scope module m2 $end
$var wire 1 u" in0 $end
$var wire 1 v" in1 $end
$var wire 1 &# select $end
$var wire 1 ## out $end
$upscope $end
$scope module m3 $end
$var wire 1 $# in0 $end
$var wire 1 ## in1 $end
$var wire 1 '# select $end
$var wire 1 x" out $end
$upscope $end
$upscope $end
$scope module m3 $end
$var wire 1 y" in0 $end
$var wire 1 x" in1 $end
$var wire 1 (# select $end
$var wire 1 U" out $end
$upscope $end
$upscope $end
$upscope $end
$scope module c2 $end
$var wire 2 )# A [1:0] $end
$var wire 2 *# B [1:0] $end
$var wire 1 $ EQ0 $end
$var wire 1 K" EQ1 $end
$var wire 1 " GT0 $end
$var wire 1 J" GT1 $end
$var wire 1 +# justin $end
$var wire 1 ,# notEQ1 $end
$var wire 1 -# notGT1 $end
$var wire 1 .# smith $end
$var wire 3 /# selectBits [2:0] $end
$var wire 2 0# notB [1:0] $end
$var wire 2 1# notA [1:0] $end
$var wire 1 2# gtmux $end
$var wire 1 3# eqmux $end
$scope module EQout $end
$var wire 1 4# in0 $end
$var wire 1 5# in1 $end
$var wire 1 6# in2 $end
$var wire 1 7# in3 $end
$var wire 1 8# in4 $end
$var wire 1 9# in5 $end
$var wire 1 :# in6 $end
$var wire 1 ;# in7 $end
$var wire 3 <# select [2:0] $end
$var wire 1 =# w2 $end
$var wire 1 ># w1 $end
$var wire 1 3# out $end
$scope module m1 $end
$var wire 1 4# in0 $end
$var wire 1 5# in1 $end
$var wire 1 6# in2 $end
$var wire 1 7# in3 $end
$var wire 2 ?# select [1:0] $end
$var wire 1 @# w2 $end
$var wire 1 A# w1 $end
$var wire 1 ># out $end
$scope module m1 $end
$var wire 1 4# in0 $end
$var wire 1 5# in1 $end
$var wire 1 B# select $end
$var wire 1 A# out $end
$upscope $end
$scope module m2 $end
$var wire 1 6# in0 $end
$var wire 1 7# in1 $end
$var wire 1 C# select $end
$var wire 1 @# out $end
$upscope $end
$scope module m3 $end
$var wire 1 A# in0 $end
$var wire 1 @# in1 $end
$var wire 1 D# select $end
$var wire 1 ># out $end
$upscope $end
$upscope $end
$scope module m2 $end
$var wire 1 8# in0 $end
$var wire 1 9# in1 $end
$var wire 1 :# in2 $end
$var wire 1 ;# in3 $end
$var wire 2 E# select [1:0] $end
$var wire 1 F# w2 $end
$var wire 1 G# w1 $end
$var wire 1 =# out $end
$scope module m1 $end
$var wire 1 8# in0 $end
$var wire 1 9# in1 $end
$var wire 1 H# select $end
$var wire 1 G# out $end
$upscope $end
$scope module m2 $end
$var wire 1 :# in0 $end
$var wire 1 ;# in1 $end
$var wire 1 I# select $end
$var wire 1 F# out $end
$upscope $end
$scope module m3 $end
$var wire 1 G# in0 $end
$var wire 1 F# in1 $end
$var wire 1 J# select $end
$var wire 1 =# out $end
$upscope $end
$upscope $end
$scope module m3 $end
$var wire 1 ># in0 $end
$var wire 1 =# in1 $end
$var wire 1 K# select $end
$var wire 1 3# out $end
$upscope $end
$upscope $end
$scope module GTout $end
$var wire 1 L# in0 $end
$var wire 1 M# in1 $end
$var wire 1 N# in2 $end
$var wire 1 O# in3 $end
$var wire 1 P# in4 $end
$var wire 1 Q# in5 $end
$var wire 1 R# in6 $end
$var wire 1 S# in7 $end
$var wire 3 T# select [2:0] $end
$var wire 1 U# w2 $end
$var wire 1 V# w1 $end
$var wire 1 2# out $end
$scope module m1 $end
$var wire 1 L# in0 $end
$var wire 1 M# in1 $end
$var wire 1 N# in2 $end
$var wire 1 O# in3 $end
$var wire 2 W# select [1:0] $end
$var wire 1 X# w2 $end
$var wire 1 Y# w1 $end
$var wire 1 V# out $end
$scope module m1 $end
$var wire 1 L# in0 $end
$var wire 1 M# in1 $end
$var wire 1 Z# select $end
$var wire 1 Y# out $end
$upscope $end
$scope module m2 $end
$var wire 1 N# in0 $end
$var wire 1 O# in1 $end
$var wire 1 [# select $end
$var wire 1 X# out $end
$upscope $end
$scope module m3 $end
$var wire 1 Y# in0 $end
$var wire 1 X# in1 $end
$var wire 1 \# select $end
$var wire 1 V# out $end
$upscope $end
$upscope $end
$scope module m2 $end
$var wire 1 P# in0 $end
$var wire 1 Q# in1 $end
$var wire 1 R# in2 $end
$var wire 1 S# in3 $end
$var wire 2 ]# select [1:0] $end
$var wire 1 ^# w2 $end
$var wire 1 _# w1 $end
$var wire 1 U# out $end
$scope module m1 $end
$var wire 1 P# in0 $end
$var wire 1 Q# in1 $end
$var wire 1 `# select $end
$var wire 1 _# out $end
$upscope $end
$scope module m2 $end
$var wire 1 R# in0 $end
$var wire 1 S# in1 $end
$var wire 1 a# select $end
$var wire 1 ^# out $end
$upscope $end
$scope module m3 $end
$var wire 1 _# in0 $end
$var wire 1 ^# in1 $end
$var wire 1 b# select $end
$var wire 1 U# out $end
$upscope $end
$upscope $end
$scope module m3 $end
$var wire 1 V# in0 $end
$var wire 1 U# in1 $end
$var wire 1 c# select $end
$var wire 1 2# out $end
$upscope $end
$upscope $end
$upscope $end
$upscope $end
$upscope $end
$upscope $end
$enddefinitions $end
$comment Show the parameter values. $end
$dumpall
$end
#0
$dumpvars
0c#
0b#
0a#
0`#
1_#
1^#
b0 ]#
0\#
0[#
0Z#
0Y#
1X#
b0 W#
0V#
1U#
b0 T#
1S#
1R#
0Q#
1P#
0O#
1N#
0M#
0L#
0K#
0J#
0I#
0H#
0G#
0F#
b0 E#
0D#
0C#
0B#
1A#
0@#
b0 ?#
1>#
0=#
b0 <#
0;#
0:#
19#
08#
07#
06#
05#
14#
13#
02#
b11 1#
b11 0#
b0 /#
0.#
1-#
1,#
0+#
b0 *#
b0 )#
0(#
0'#
0&#
0%#
1$#
1##
b0 "#
0!#
0~"
0}"
0|"
1{"
b0 z"
0y"
1x"
b0 w"
1v"
1u"
0t"
1s"
0r"
1q"
0p"
0o"
0n"
0m"
0l"
0k"
0j"
0i"
b0 h"
0g"
0f"
0e"
1d"
0c"
b0 b"
1a"
0`"
b0 _"
0^"
0]"
1\"
0["
0Z"
0Y"
0X"
1W"
1V"
0U"
b11 T"
b11 S"
b0 R"
0Q"
1P"
1O"
0N"
b0 M"
b0 L"
0K"
0J"
b0 I"
b0 H"
0G"
0F"
0E"
0D"
1C"
1B"
b0 A"
0@"
0?"
0>"
0="
1<"
b0 ;"
0:"
19"
b0 8"
17"
16"
05"
14"
03"
12"
01"
00"
0/"
0."
0-"
0,"
0+"
0*"
b0 )"
0("
0'"
0&"
1%"
0$"
b0 #"
1""
0!"
b0 ~
0}
0|
1{
0z
0y
0x
0w
1v
1u
0t
b11 s
b11 r
b0 q
0p
1o
1n
0m
b0 l
b0 k
0j
0i
0h
0g
1f
1e
b0 d
0c
0b
0a
0`
1_
b0 ^
0]
1\
b0 [
1Z
1Y
0X
1W
0V
1U
0T
0S
0R
0Q
0P
0O
0N
0M
b0 L
0K
0J
0I
1H
0G
b0 F
1E
0D
b0 C
0B
0A
1@
0?
0>
0=
0<
1;
1:
09
b11 8
b11 7
b0 6
05
14
13
02
b0 1
b0 0
0/
0.
b0 -
b0 ,
0+
0*
b0 )
b0 (
b0 '
b0 &
b0 %
0$
0#
0"
0!
$end
#200
1"
0-#
1.#
1J"
0P"
1Q"
1*
0o
1p
1.
04
15
1!
b1 '
#400
0"
0,#
1$
1-#
0.#
1K"
0J"
1P"
0Q"
0O"
0*
0n
1+
1o
0p
1/
0.
14
05
03
0!
1#
b10 '
#600
1,#
0$
1O"
0K"
1n
0+
0/
04
1!
b11 '
#800
03#
0>#
0A#
0X#
04#
09#
0N#
0S#
b10 0#
1@#
16#
1;#
b1 *#
14
13
b1 I"
0!
0#
b1 %
b1 )
b100 '
#1000
1"
0-#
1.#
1J"
0P"
1Q"
1*
0o
1p
1.
04
15
1!
b101 '
#1200
0"
0,#
1-#
0.#
1K"
0J"
1P"
0Q"
0O"
0*
0n
1+
1o
0p
1/
0.
14
05
03
0!
1#
b110 '
#1400
1,#
1O"
0K"
1n
0+
0/
04
1!
b111 '
#1600
1=#
0U#
1G#
0_#
14#
19#
1N#
1S#
1B#
1C#
1H#
1I#
1Z#
1[#
1`#
1a#
b1 0#
b1 ?#
b1 E#
b1 W#
b1 ]#
0@#
b1 /#
b1 <#
b1 T#
06#
0;#
b10 *#
14
13
b10 I"
0!
0#
b10 %
b10 )
b1000 '
#1800
1"
0-#
1.#
1J"
0P"
1Q"
1*
0o
1p
1.
04
15
1!
b1001 '
#2000
0"
0,#
1-#
0.#
1K"
0J"
1P"
0Q"
0O"
0*
0n
1+
1o
0p
1/
0.
14
05
03
0!
1#
b1010 '
#2200
1,#
1O"
0K"
1n
0+
0/
04
1!
b1011 '
#2400
0=#
0G#
0^#
04#
09#
0N#
0S#
b0 0#
1F#
16#
1;#
b11 *#
14
13
b11 I"
0!
0#
b11 %
b11 )
b1100 '
#2600
1"
0-#
1.#
1J"
0P"
1Q"
1*
0o
1p
1.
04
15
1!
b1101 '
#2800
0"
0,#
1-#
0.#
1K"
0J"
1P"
0Q"
0O"
0*
0n
1+
1o
0p
1/
0.
14
05
03
0!
1#
b1110 '
#3000
1,#
1O"
0K"
1n
0+
0/
04
1!
b1111 '
#3200
0V"
13#
0a"
1>#
1U#
0d"
0{"
1A#
1X#
1_#
1^#
0W"
0\"
0q"
0v"
14#
19#
1N#
1S#
0B#
0C#
0H#
0I#
0Z#
0[#
0`#
0a#
b10 S"
1c"
b11 0#
b0 ?#
b0 E#
b0 W#
b0 ]#
0F#
1Y"
1^"
b0 /#
b0 <#
b0 T#
06#
0;#
b1 M"
b0 *#
14
13
b100 I"
0!
0#
b100 %
b100 )
b10000 '
#3400
1"
0-#
1.#
1J"
0P"
1Q"
1*
0o
1p
1.
04
15
1!
b10001 '
#3600
0"
1-#
0.#
0J"
1P"
0Q"
0O"
0*
0n
1+
1o
0p
1/
0.
14
05
03
0!
1#
b10010 '
#3800
1O"
1n
0+
0/
04
1!
b10011 '
#4000
03#
0>#
0A#
0X#
04#
09#
0N#
0S#
b10 0#
1@#
16#
1;#
b1 *#
14
13
b101 I"
0!
0#
b101 %
b101 )
b10100 '
#4200
1"
0-#
1.#
1J"
0P"
1Q"
1*
0o
1p
1.
04
15
1!
b10101 '
#4400
0"
1-#
0.#
0J"
1P"
0Q"
0O"
0*
0n
1+
1o
0p
1/
0.
14
05
03
0!
1#
b10110 '
#4600
1O"
1n
0+
0/
04
1!
b10111 '
#4800
1=#
0U#
1G#
0_#
14#
19#
1N#
1S#
1B#
1C#
1H#
1I#
1Z#
1[#
1`#
1a#
b1 0#
b1 ?#
b1 E#
b1 W#
b1 ]#
0@#
b1 /#
b1 <#
b1 T#
06#
0;#
b10 *#
14
13
b110 I"
0!
0#
b110 %
b110 )
b11000 '
#5000
1"
0-#
1.#
1J"
0P"
1Q"
1*
0o
1p
1.
04
15
1!
b11001 '
#5200
0"
1-#
0.#
0J"
1P"
0Q"
0O"
0*
0n
1+
1o
0p
1/
0.
14
05
03
0!
1#
b11010 '
#5400
1O"
1n
0+
0/
04
1!
b11011 '
#5600
0=#
0G#
0^#
04#
09#
0N#
0S#
b0 0#
1F#
16#
1;#
b11 *#
14
13
b111 I"
0!
0#
b111 %
b111 )
b11100 '
#5800
1"
0-#
1.#
1J"
0P"
1Q"
1*
0o
1p
1.
04
15
1!
b11101 '
#6000
0"
1-#
0.#
0J"
1P"
0Q"
0O"
0*
0n
1+
1o
0p
1/
0.
14
05
03
0!
1#
b11110 '
#6200
1O"
1n
0+
0/
04
1!
b11111 '
#6400
13#
1`"
0x"
1>#
1U#
1j"
0$#
1A#
1X#
1_#
1^#
1W"
1\"
1q"
1v"
1e"
1f"
1k"
1l"
1}"
1~"
1%#
1&#
14#
19#
1N#
1S#
0B#
0C#
0H#
0I#
0Z#
0[#
0`#
0a#
b1 S"
b1 b"
b1 h"
b1 z"
b1 "#
0c"
b11 0#
b0 ?#
b0 E#
b0 W#
b0 ]#
0F#
b1 R"
b1 _"
b1 w"
0Y"
0^"
b0 /#
b0 <#
b0 T#
06#
0;#
b10 M"
b0 *#
14
13
b1000 I"
0!
0#
b1000 %
b1000 )
b100000 '
#6600
1"
0-#
1.#
1J"
0P"
1Q"
1*
0o
1p
1.
04
15
1!
b100001 '
#6800
0"
1-#
0.#
0J"
1P"
0Q"
0O"
0*
0n
1+
1o
0p
1/
0.
14
05
03
0!
1#
b100010 '
#7000
1O"
1n
0+
0/
04
1!
b100011 '
#7200
03#
0>#
0A#
0X#
04#
09#
0N#
0S#
b10 0#
1@#
16#
1;#
b1 *#
14
13
b1001 I"
0!
0#
b1001 %
b1001 )
b100100 '
