alu/adder/nand_adder.v
module nand_adder(S, Cout, A, B, Cin);
    input A, B, Cin;
    output S, Cout;

    wire w1, w2, w3, w4, w5, w6, w7;
    
    nand n1(w1, A, B);  // L1
    nand n2(w2, w1, A); // L2
    nand n3(w3, w1, B);
    nand n4(w4, w2, w3); // L3
    nand n5(w5, w4, Cin); // L4
    nand n6(w6, w4, w5); // L5
    nand n7(w7, w5, Cin);
    nand n8(S, w6, w7); // L6
    nand n9(Cout, w5, w1);
endmodule

alu/adder/nand_adder_tb.v
`timescale 1 ns / 100 ps
module nand_adder_tb;
    reg A, B, Cin;
    wire S, Cout;

    nand_adder adder(.S(S), .Cout(Cout), .A(A), .B(B), .Cin(Cin));

    initial begin
        A = 0; B = 0; Cin = 0;
        #80; $finish;
    end

    always 
        #10 A = ~A;
    always 
        #20 B = ~B;
    always
        #40 Cin = ~Cin;

    always @(A, B, Cin) begin
        #1;
        $display("A = %b, B = %b, Cin = %b, S = %b, Cout = %b", A, B, Cin, S, Cout);
    end

    initial begin
        $dumpfile("nand_adder_tb.vcd");
        $dumpvars(0, nand_adder_tb);
    end

endmodule

alu/adder/nand_adder_tb.vcd
$date
	Fri Jan 26 10:24:56 2024
$end
$version
	Icarus Verilog
$end
$timescale
	100ps
$end
$scope module nand_adder_tb $end
$var wire 1 ! S $end
$var wire 1 " Cout $end
$var reg 1 # A $end
$var reg 1 $ B $end
$var reg 1 % Cin $end
$scope module adder $end
$var wire 1 # A $end
$var wire 1 $ B $end
$var wire 1 % Cin $end
$var wire 1 " Cout $end
$var wire 1 ! S $end
$var wire 1 & w1 $end
$var wire 1 ' w2 $end
$var wire 1 ( w3 $end
$var wire 1 ) w4 $end
$var wire 1 * w5 $end
$var wire 1 + w6 $end
$var wire 1 , w7 $end
$upscope $end
$upscope $end
$enddefinitions $end
$comment Show the parameter values. $end
$dumpall
$end
#0
$dumpvars
1,
1+
1*
0)
1(
1'
1&
0%
0$
0#
0"
0!
$end
#100
1!
0+
1)
0'
1#
#200
1'
0(
0#
1$
#300
0!
1+
0)
1(
1"
0&
1'
1#
#400
0"
1!
1&
0,
0#
0$
1%
#500
0!
1,
1"
0*
1+
1)
0'
1#
#600
1'
0(
0#
1$
#700
1!
0,
1*
0)
1(
0&
1'
1#
#800
0"
0!
1&
1,
0#
0$
0%
