alu/adder/1bit_adder.v
module bit_adder(S, Cout, A, B, Cin);
    input A, B, Cin;
    output S, Cout;
    
    wire w1, w2, w3;
    
    xor Sresult(S, A, B, Cin);
    and A_and_B(w1, A, B);
    and A_and_Cin(w2, A, Cin);
    and B_and_Cin(w3, B, Cin);
    or out(Cout, w1, w2, w3);
endmodule

alu/adder/2bit_adder.v
module two_bit_adder(S, Cout, A, B, Cin);
    input [1:0] A, B;
    input Cin;
    output [1:0] S;
    output Cout;
    
    wire w1;
    
    bit_adder fa1(S[0], w1, A[0], B[0], Cin);
    bit_adder fa2(S[1], Cout, A[1], B[1], w1);
endmodule

alu/adder/2bit_adder_tb.v
`timescale 1 ns / 100 ps
module two_bit_adder_tb;
    reg [1:0] A, B;
    reg Cin;
    wire [1:0] S;
    wire Cout;

    two_bit_adder adder(.A(A), .B(B), .Cin(Cin), .S(S), .Cout(Cout));

    initial begin
        A = 0; B = 0; Cin = 0;
        #320; $finish;
    end

    always 
        #10 A[0] = ~A[0];
    always 
        #20 A[1] = ~A[1];
    always
        #40 B[0] = ~B[0];
    always
        #80 B[1] = ~B[1];
    always
        #160 Cin = ~Cin;

    always @(A, B, Cin) begin
        #1;
        $display("A = %b, B = %b, Cin = %b, S = %b, Cout = %b", A, B, Cin, S, Cout);
    end

    initial begin
        $dumpfile("2bit_adder_tb.vcd");
        $dumpvars(0, two_bit_adder_tb);
    end
endmodule

alu/adder/two_bit_adder_tb.vcd
$date
	Fri Jan 19 11:02:35 2024
$end
$version
	Icarus Verilog
$end
$timescale
	100ps
$end
$scope module two_bit_adder_tb $end
$var wire 2 ! S [1:0] $end
$var wire 1 " Cout $end
$var reg 2 # A [1:0] $end
$var reg 2 $ B [1:0] $end
$var reg 1 % Cin $end
$scope module adder $end
$var wire 2 & A [1:0] $end
$var wire 2 ' B [1:0] $end
$var wire 1 % Cin $end
$var wire 1 ( w1 $end
$var wire 2 ) S [1:0] $end
$var wire 1 " Cout $end
$scope module fa1 $end
$var wire 1 * A $end
$var wire 1 + B $end
$var wire 1 % Cin $end
$var wire 1 ( Cout $end
$var wire 1 , S $end
$var wire 1 - w1 $end
$var wire 1 . w2 $end
$var wire 1 / w3 $end
$upscope $end
$scope module fa2 $end
$var wire 1 0 A $end
$var wire 1 1 B $end
$var wire 1 ( Cin $end
$var wire 1 " Cout $end
$var wire 1 2 S $end
$var wire 1 3 w1 $end
$var wire 1 4 w2 $end
$var wire 1 5 w3 $end
$upscope $end
$upscope $end
$upscope $end
$enddefinitions $end
$comment Show the parameter values. $end
$dumpall
$end
#0
$dumpvars
05
04
03
02
01
00
0/
0.
0-
0,
0+
0*
b0 )
0(
b0 '
b0 &
0%
b0 $
b0 #
0"
b0 !
$end
#100
b1 !
b1 )
1,
1*
b1 #
b1 &
#200
0,
b10 !
b10 )
12
0*
10
b10 #
b10 &
#300
b11 !
b11 )
1,
1*
b11 #
b11 &
#400
b1 !
b1 )
02
0*
00
1+
b0 #
b0 &
b1 $
b1 '
#500
12
1(
b10 !
b10 )
0,
1-
1*
b1 #
b1 &
#600
0(
0"
1,
0-
b11 !
b11 )
12
04
0*
10
b10 #
b10 &
#700
1"
02
14
1(
b0 !
b0 )
0,
1-
1*
b11 #
b11 &
#800
0"
b10 !
b10 )
12
0(
04
0-
05
0*
00
0+
11
b0 #
b0 &
b10 $
b10 '
#900
b11 !
b11 )
1,
1*
b1 #
b1 &
#1000
1"
0,
b0 !
b0 )
02
13
0*
10
b10 #
b10 &
#1100
b1 !
b1 )
1,
1*
b11 #
b11 &
#1200
0"
b11 !
b11 )
12
03
0*
00
1+
b0 #
b0 &
b11 $
b11 '
#1300
1"
02
15
1(
b0 !
b0 )
0,
1-
1*
b1 #
b1 &
#1400
05
0(
1,
0-
b1 !
b1 )
02
13
04
0*
10
b10 #
b10 &
#1500
12
14
15
1(
b10 !
b10 )
0,
1-
1*
b11 #
b11 &
#1600
02
0(
0"
04
0-
03
05
0*
00
0+
01
b1 !
b1 )
1,
0.
0/
b0 #
b0 &
b0 $
b0 '
1%
#1700
12
1(
b10 !
b10 )
0,
1.
1*
b1 #
b1 &
#1800
0(
0"
1,
0.
b11 !
b11 )
12
04
0*
10
b10 #
b10 &
#1900
1"
02
14
1(
b0 !
b0 )
0,
1.
1*
b11 #
b11 &
#2000
0"
0.
b10 !
b10 )
12
04
1/
0*
00
1+
b0 #
b0 &
b1 $
b1 '
#2100
b11 !
b11 )
1,
1-
1.
1*
b1 #
b1 &
#2200
1"
0,
0-
0.
b0 !
b0 )
02
14
0*
10
b10 #
b10 &
#2300
b1 !
b1 )
1,
1-
1.
1*
b11 #
b11 &
#2400
0"
b11 !
b11 )
12
0(
0.
04
0-
0/
05
0*
00
0+
11
b0 #
b0 &
b10 $
b10 '
#2500
1"
02
15
1(
b0 !
b0 )
0,
1.
1*
b1 #
b1 &
#2600
05
0(
1,
0.
b1 !
b1 )
02
13
04
0*
10
b10 #
b10 &
#2700
12
14
15
1(
b10 !
b10 )
0,
1.
1*
b11 #
b11 &
#2800
0.
b0 !
b0 )
02
03
04
1/
0*
00
1+
b0 #
b0 &
b11 $
b11 '
#2900
b1 !
b1 )
1,
1-
1.
1*
b1 #
b1 &
#3000
0,
0-
0.
b10 !
b10 )
12
13
14
0*
10
b10 #
b10 &
#3100
b11 !
b11 )
1,
1-
1.
1*
b11 #
b11 &
#3200
02
0(
0"
04
0-
03
05
0*
00
0+
01
b0 !
b0 )
0,
0.
0/
b0 #
b0 &
b0 $
b0 '
0%
